thtagger/__init__.py
thtagger/__main__.py
thtagger/forms/__init__.py
thtagger/forms/aboutDialog.py
thtagger/forms/mainWindow.py
thtagger/models/__init__.py
thtagger/models/fileList.py
thtagger/models/metadata.py
thtagger/models/tagEditor.py
thtagger/models/thtException.py
thtagger/ui/__init__.py
thtagger/ui/rc_Thtagger.py
thtagger/ui/ui_AboutDialog.py
thtagger/ui/ui_MainWindow.py
thtagger/utils/__init__.py
thtagger/utils/cache.py
thtagger/utils/localDb.py
thtagger/utils/remoteDb.py
thtagger-0.0.3.dist-info/LICENSE
thtagger-0.0.3.dist-info/METADATA
thtagger-0.0.3.dist-info/WHEEL
thtagger-0.0.3.dist-info/top_level.txt
thtagger-0.0.3.dist-info/RECORD
